.gitignore
CHANGES.txt
README.rst
bootstrap.py
buildout.cfg
setup.cfg
setup.py
ptah_crowd/__init__.py
ptah_crowd/login.py
ptah_crowd/memberprops.py
ptah_crowd/module.py
ptah_crowd/provider.py
ptah_crowd/registration.py
ptah_crowd/resetpassword.py
ptah_crowd/schemas.py
ptah_crowd/settings.py
ptah_crowd/user.py
ptah_crowd/validation.py
ptah_crowd/views.py
ptah_crowd.egg-info/PKG-INFO
ptah_crowd.egg-info/SOURCES.txt
ptah_crowd.egg-info/dependency_links.txt
ptah_crowd.egg-info/not-zip-safe
ptah_crowd.egg-info/requires.txt
ptah_crowd.egg-info/top_level.txt
ptah_crowd/templates/login-success.pt
ptah_crowd/templates/login-suspended.pt
ptah_crowd/templates/login.pt
ptah_crowd/templates/resetpassword.pt
ptah_crowd/templates/resetpasswordform.pt
ptah_crowd/templates/resetpasswordmail.pt
ptah_crowd/templates/users.pt
ptah_crowd/templates/validate_email.txt
ptah_crowd/tests/__init__.py
ptah_crowd/tests/test_join.py
ptah_crowd/tests/test_login.py
ptah_crowd/tests/test_memberprops.py
ptah_crowd/tests/test_module.py
ptah_crowd/tests/test_provider.py
ptah_crowd/tests/test_resetpassword.py
ptah_crowd/tests/test_user.py
ptah_crowd/tests/test_validation.py
ptah_crowd/tests/test_validators.py